loyverse/__init__.py
loyverse/api.py
loyverse/client.py
loyverse/exceptions.py
loyverse-0.1.0.dist-info/LICENSE
loyverse-0.1.0.dist-info/METADATA
loyverse-0.1.0.dist-info/WHEEL
loyverse-0.1.0.dist-info/top_level.txt
loyverse-0.1.0.dist-info/RECORD
