Metadata-Version: 2.1
Name: loyverse
Version: 0.1.0
Summary: Loyverse API wrapper
Home-page: https://loyverse.readthedocs.io
Maintainer: Matteo Berchier
Maintainer-email: maberchier@gmail.com
License: MIT
Project-URL: Bug Tracker, https://github.com/matteobe/loyverse/issues
Project-URL: Documentation, https://loyverse.readthedocs.io
Project-URL: Source Code, https://github.com/matteobe/loyverse
Platform: UNKNOWN
Requires-Python: >3.7.0
Requires-Dist: requests
Requires-Dist: python-dotenv
Requires-Dist: pandas
